Workbook

Sheet grade_pricing
A1: grade | B1: _FREQ_ | C1: avg_pred_prob | D1: avg_int_rate | E1: avg_loan_amnt | F1: avg_actual_default | G1: avg_LGD_by_Grade | H1: Fair Rate | I1: Rate Gap | J1: expected loss on default | K1: breakeven interest rate
A2: A | B2: 226316 | C2: 0.060866597 | D2: 7.12497 | E2: 13871.264 | F2: 15.551471 | G2: =(13677-5641-788)/13677 -> 0.52994078 | H2: =C2*$G2*($B$18)+$B$15+$B$16 -> 0.093185222 | I2: =D2/100-H2 -> -0.021935522 | J2: =C2*$G2*$B$18 -> 0.023185222 | K2: =J2+$B$15 -> 0.073185222
A3: B | B3: 380442 | C3: 0.13448042 | D3: 10.688206 | E3: 13222.898 | F3: 17.283975 | G3: =(13522-4887-869)/13522 -> 0.57432332 | H3: =C3*$G3*($B$18)+$B$15+$B$16 -> 0.12551629 | I3: =D3/100-H3 -> -0.01863423 | J3: =C3*$G3*$B$18 -> 0.055516287 | K3: =J3+$B$15 -> 0.10551629
A4: C | B4: 370449 | C4: 0.22511061 | D4: 14.018544 | E4: 14167.424 | F4: 18.782641 | G4: =(14698-4415-1058)/14698 -> 0.62763641 | H4: =C4*$G4*($B$18)+$B$15+$B$16 -> 0.1715568 | I4: =D4/100-H4 -> -0.031371355 | J4: =C4*$G4*$B$18 -> 0.1015568 | K4: =J4+$B$15 -> 0.1515568
A5: D | B5: 195926 | C5: 0.30435981 | D5: 17.688413 | E5: 15238.09 | F5: 19.991315 | G5: =(15957-4418-1237)/15957 -> 0.64561008 | H5: =C5*$G5*($B$18)+$B$15+$B$16 -> 0.21124156 | I5: =D5/100-H5 -> -0.034357427 | J5: =C5*$G5*$B$18 -> 0.14124156 | K5: =J5+$B$15 -> 0.19124156
A6: E | B6: 92088 | C6: 0.38573973 | D6: 21.069554 | E6: 17587.172 | F6: 20.595635 | G6: =(18091-3927-1557)/18091 -> 0.69686584 | H6: =C6*$G6*($B$18)+$B$15+$B$16 -> 0.26321838 | I6: =D6/100-H6 -> -0.052522843 | J6: =C6*$G6*$B$18 -> 0.19321838 | K6: =J6+$B$15 -> 0.24321838
A7: F | B7: 31721 | C7: 0.4525078 | D7: 24.838365 | E7: 19046.351 | F7: 20.798292 | G7: =(19515-3439-1820)/19515 -> 0.73051499 | H7: =C7*$G7*($B$18)+$B$15+$B$16 -> 0.30760748 | I7: =D7/100-H7 -> -0.059223822 | J7: =C7*$G7*$B$18 -> 0.23760748 | K7: =J7+$B$15 -> 0.28760748
A8: G | B8: 9139 | C8: 0.49786629 | D8: 27.499757 | E8: 20422.229 | F8: 21.040834 | G8: =(20334-2887-1932)/20334 -> 0.76300777 | H8: =C8*$G8*($B$18)+$B$15+$B$16 -> 0.34305277 | I8: =D8/100-H8 -> -0.068055195 | J8: =C8*$G8*$B$18 -> 0.27305277 | K8: =J8+$B$15 -> 0.32305277
A11: Average funded amount | B11: 15521.83
A12: average total principle recovered | B12: 4364.82
A13: average recoveries | B13: 1172.18
A15: Cost of funds | B15: 0.05
A16: Profit margin | B16: 0.02
A17: Average EAD | B17: =B11-B12 -> 11157.01
A18: average EAD ratio | B18: =B17/B11 -> 0.71879476

Sheet sensitivity analysis
A5: Cost of funds sensitivity table fair rate
B6: default prediction proability | C6: 0.03 | D6: 0.05 | E6: 0.07 | F6: 0.09
A7: A | B7: 0.060866597 | C7: =$B7*VLOOKUP($A7,'Grade Overlay'!$A$2:$B$8,2,FALSE())*grade_pricing!$B$18+C$6+grade_pricing!$B$16 -> 0.073185222 | D7: =$B7*VLOOKUP($A7,'Grade Overlay'!$A$2:$B$8,2,FALSE())*grade_pricing!$B$18+D$6+grade_pricing!$B$16 -> 0.093185222 | E7: =$B7*VLOOKUP($A7,'Grade Overlay'!$A$2:$B$8,2,FALSE())*grade_pricing!$B$18+E$6+grade_pricing!$B$16 -> 0.11318522 | F7: =$B7*VLOOKUP($A7,'Grade Overlay'!$A$2:$B$8,2,FALSE())*grade_pricing!$B$18+F$6+grade_pricing!$B$16 -> 0.13318522
A8: B | B8: 0.13448042 | C8: =$B8*VLOOKUP($A8,'Grade Overlay'!$A$2:$B$8,2,FALSE())*grade_pricing!$B$18+C$6+grade_pricing!$B$16 -> 0.10551629 | D8: =$B8*VLOOKUP($A8,'Grade Overlay'!$A$2:$B$8,2,FALSE())*grade_pricing!$B$18+D$6+grade_pricing!$B$16 -> 0.12551629 | E8: =$B8*VLOOKUP($A8,'Grade Overlay'!$A$2:$B$8,2,FALSE())*grade_pricing!$B$18+E$6+grade_pricing!$B$16 -> 0.14551629 | F8: =$B8*VLOOKUP($A8,'Grade Overlay'!$A$2:$B$8,2,FALSE())*grade_pricing!$B$18+F$6+grade_pricing!$B$16 -> 0.16551629
A9: C | B9: 0.22511061 | C9: =$B9*VLOOKUP($A9,'Grade Overlay'!$A$2:$B$8,2,FALSE())*grade_pricing!$B$18+C$6+grade_pricing!$B$16 -> 0.1515568 | D9: =$B9*VLOOKUP($A9,'Grade Overlay'!$A$2:$B$8,2,FALSE())*grade_pricing!$B$18+D$6+grade_pricing!$B$16 -> 0.1715568 | E9: =$B9*VLOOKUP($A9,'Grade Overlay'!$A$2:$B$8,2,FALSE())*grade_pricing!$B$18+E$6+grade_pricing!$B$16 -> 0.1915568 | F9: =$B9*VLOOKUP($A9,'Grade Overlay'!$A$2:$B$8,2,FALSE())*grade_pricing!$B$18+F$6+grade_pricing!$B$16 -> 0.2115568
A10: D | B10: 0.30435981 | C10: =$B10*VLOOKUP($A10,'Grade Overlay'!$A$2:$B$8,2,FALSE())*grade_pricing!$B$18+C$6+grade_pricing!$B$16 -> 0.19124156 | D10: =$B10*VLOOKUP($A10,'Grade Overlay'!$A$2:$B$8,2,FALSE())*grade_pricing!$B$18+D$6+grade_pricing!$B$16 -> 0.21124156 | E10: =$B10*VLOOKUP($A10,'Grade Overlay'!$A$2:$B$8,2,FALSE())*grade_pricing!$B$18+E$6+grade_pricing!$B$16 -> 0.23124156 | F10: =$B10*VLOOKUP($A10,'Grade Overlay'!$A$2:$B$8,2,FALSE())*grade_pricing!$B$18+F$6+grade_pricing!$B$16 -> 0.25124156
A11: E | B11: 0.38573973 | C11: =$B11*VLOOKUP($A11,'Grade Overlay'!$A$2:$B$8,2,FALSE())*grade_pricing!$B$18+C$6+grade_pricing!$B$16 -> 0.24321838 | D11: =$B11*VLOOKUP($A11,'Grade Overlay'!$A$2:$B$8,2,FALSE())*grade_pricing!$B$18+D$6+grade_pricing!$B$16 -> 0.26321838 | E11: =$B11*VLOOKUP($A11,'Grade Overlay'!$A$2:$B$8,2,FALSE())*grade_pricing!$B$18+E$6+grade_pricing!$B$16 -> 0.28321838 | F11: =$B11*VLOOKUP($A11,'Grade Overlay'!$A$2:$B$8,2,FALSE())*grade_pricing!$B$18+F$6+grade_pricing!$B$16 -> 0.30321838
A12: F | B12: 0.4525078 | C12: =$B12*VLOOKUP($A12,'Grade Overlay'!$A$2:$B$8,2,FALSE())*grade_pricing!$B$18+C$6+grade_pricing!$B$16 -> 0.28760748 | D12: =$B12*VLOOKUP($A12,'Grade Overlay'!$A$2:$B$8,2,FALSE())*grade_pricing!$B$18+D$6+grade_pricing!$B$16 -> 0.30760748 | E12: =$B12*VLOOKUP($A12,'Grade Overlay'!$A$2:$B$8,2,FALSE())*grade_pricing!$B$18+E$6+grade_pricing!$B$16 -> 0.32760748 | F12: =$B12*VLOOKUP($A12,'Grade Overlay'!$A$2:$B$8,2,FALSE())*grade_pricing!$B$18+F$6+grade_pricing!$B$16 -> 0.34760748
A13: G | B13: 0.49786629 | C13: =$B13*VLOOKUP($A13,'Grade Overlay'!$A$2:$B$8,2,FALSE())*grade_pricing!$B$18+C$6+grade_pricing!$B$16 -> 0.32305277 | D13: =$B13*VLOOKUP($A13,'Grade Overlay'!$A$2:$B$8,2,FALSE())*grade_pricing!$B$18+D$6+grade_pricing!$B$16 -> 0.34305277 | E13: =$B13*VLOOKUP($A13,'Grade Overlay'!$A$2:$B$8,2,FALSE())*grade_pricing!$B$18+E$6+grade_pricing!$B$16 -> 0.36305277 | F13: =$B13*VLOOKUP($A13,'Grade Overlay'!$A$2:$B$8,2,FALSE())*grade_pricing!$B$18+F$6+grade_pricing!$B$16 -> 0.38305277

Sheet Grade Overlay
A1: Grade | B1: LGD | C1: Lending Club Average Rate | D1: Breakever Rate | E1: Fair rate | F1: Fair Rate gap | G1: Mispriced? | H1: breakeven rate gap
A2: A | B2: =grade_pricing!G2 -> 0.52994078 | C2: =7.124970042/100 -> 0.0712497 | D2: =grade_pricing!K2 -> 0.073185222 | E2: =grade_pricing!H2 -> 0.093185222 | F2: =C2-E2 -> -0.021935522 | G2: =IF(C2 < D2, "Below Breakeven", "Above Breakeven") -> Below Breakeven | H2: =C2-D2 -> -0.0019355216
A3: B | B3: =grade_pricing!G3 -> 0.57432332 | C3: =10.68820564/100 -> 0.10688206 | D3: =grade_pricing!K3 -> 0.10551629 | E3: =grade_pricing!H3 -> 0.12551629 | F3: =C3-E3 -> -0.01863423 | G3: =IF(C3 < D3, "Below Breakeven", "Above Breakeven") -> Above Breakeven | H3: =C3-D3 -> 0.0013657695
A4: C | B4: =grade_pricing!G4 -> 0.62763641 | C4: =14.0185442/100 -> 0.14018544 | D4: =grade_pricing!K4 -> 0.1515568 | E4: =grade_pricing!H4 -> 0.1715568 | F4: =C4-E4 -> -0.031371355 | G4: =IF(C4 < D4, "Below Breakeven", "Above Breakeven") -> Below Breakeven | H4: =C4-D4 -> -0.011371355
A5: D | B5: =grade_pricing!G5 -> 0.64561008 | C5: =17.68841318/100 -> 0.17688413 | D5: =grade_pricing!K5 -> 0.19124156 | E5: =grade_pricing!H5 -> 0.21124156 | F5: =C5-E5 -> -0.034357427 | G5: =IF(C5 < D5, "Below Breakeven", "Above Breakeven") -> Below Breakeven | H5: =C5-D5 -> -0.014357427
A6: E | B6: =grade_pricing!G6 -> 0.69686584 | C6: =21.06955423/100 -> 0.21069554 | D6: =grade_pricing!K6 -> 0.24321838 | E6: =grade_pricing!H6 -> 0.26321838 | F6: =C6-E6 -> -0.052522843 | G6: =IF(C6 < D6, "Below Breakeven", "Above Breakeven") -> Below Breakeven | H6: =C6-D6 -> -0.032522843
A7: F | B7: =grade_pricing!G7 -> 0.73051499 | C7: =24.83836544/100 -> 0.24838365 | D7: =grade_pricing!K7 -> 0.28760748 | E7: =grade_pricing!H7 -> 0.30760748 | F7: =C7-E7 -> -0.059223822 | G7: =IF(C7 < D7, "Below Breakeven", "Above Breakeven") -> Below Breakeven | H7: =C7-D7 -> -0.039223822
A8: G | B8: =grade_pricing!G8 -> 0.76300777 | C8: =27.49975709/100 -> 0.27499757 | D8: =grade_pricing!K8 -> 0.32305277 | E8: =grade_pricing!H8 -> 0.34305277 | F8: =C8-E8 -> -0.068055195 | G8: =IF(C8 < D8, "Below Breakeven", "Above Breakeven") -> Below Breakeven | H8: =C8-D8 -> -0.048055195
